subprocessmonkey/README.MD
subprocessmonkey/__init__.py
subprocessmonkey/requirements.txt
subprocessmonkey/thirdparty.json
subprocessmonkey-0.10.dist-info/LICENSE.rst
subprocessmonkey-0.10.dist-info/METADATA
subprocessmonkey-0.10.dist-info/WHEEL
subprocessmonkey-0.10.dist-info/top_level.txt
subprocessmonkey-0.10.dist-info/RECORD
