Metadata-Version: 2.1
Name: subprocessmonkey
Version: 0.10
Summary: Monkey patch for subprocess to use 8.3 filenames - Windows only (no dependencies)
Home-page: https://github.com/hansalemaos/subprocessmonkey
Author: Johannes Fischer
Author-email: aulasparticularesdealemaosp@gmail.com
License: MIT
Keywords: subprocess,8.3,subproc
Classifier: Development Status :: 4 - Beta
Classifier: Programming Language :: Python :: 3 :: Only
Classifier: Programming Language :: Python :: 3.10
Classifier: Topic :: Software Development :: Libraries :: Python Modules
Classifier: Topic :: Utilities
License-File: LICENSE.rst
